codeink_cli.py
codeink-1.0.dist-info/RECORD
codeink-1.0.dist-info/entry_points.txt
codeink-1.0.dist-info/WHEEL
codeink-1.0.dist-info/metadata.json
codeink-1.0.dist-info/top_level.txt
codeink-1.0.dist-info/DESCRIPTION.rst
codeink-1.0.dist-info/METADATA
codeink/artist.py
codeink/__init__.py
codeink/canvas/canvas.html
codeink/canvas/cubism.css
codeink/canvas/__init__.py
codeink/canvas/hand.js
codeink/atelier/draftsman.py
codeink/atelier/scientist.py
codeink/atelier/__init__.py
codeink/atelier/secretary.py
codeink/parchment/tools.py
codeink/parchment/pkginfo.py
codeink/parchment/__init__.py
codeink/parchment/peephole.py
