Metadata-Version: 2.0
Name: codeink
Version: 1.0
Summary: codeink draws your Python source code into beautiful graph structures
Home-page: https://github.com/carocad/codeInk
Author: Camilo Roca
Author-email: carocad@unal.edu.co
License: Apache license 2.0 (see LICENSE)
Keywords: graph,drawings,module,complexity,maintainability,imports,structure
Platform: UNKNOWN
Classifier: Development Status :: 3 - Alpha
Classifier: Intended Audience :: Developers
Classifier: Topic :: Utilities
Classifier: Environment :: Console
Classifier: Intended Audience :: Developers
Classifier: Topic :: Software Development
Classifier: Topic :: Software Development :: Quality Assurance
Classifier: Programming Language :: Python :: 2.7
Classifier: Programming Language :: Python :: 2.6
Classifier: Programming Language :: Python :: 3
Classifier: Programming Language :: Python :: 3.2
Classifier: Programming Language :: Python :: 3.3
Classifier: Programming Language :: Python :: 3.4
Requires-Dist: docopt (>=0.6.2)
Requires-Dist: networkx (>=1.9.1)
Requires-Dist: radon (>=1.2)
Requires-Dist: astunparse (>=1.2)
